odoo/addons/stock_picking_late_activity/README.rst
odoo/addons/stock_picking_late_activity/__init__.py
odoo/addons/stock_picking_late_activity/__manifest__.py
odoo/addons/stock_picking_late_activity/data/ir_cron_data.xml
odoo/addons/stock_picking_late_activity/data/mail_activity_type_data.xml
odoo/addons/stock_picking_late_activity/i18n/es.po
odoo/addons/stock_picking_late_activity/i18n/stock_picking_late_activity.pot
odoo/addons/stock_picking_late_activity/models/__init__.py
odoo/addons/stock_picking_late_activity/models/stock_picking.py
odoo/addons/stock_picking_late_activity/models/stock_picking_type.py
odoo/addons/stock_picking_late_activity/readme/CONFIGURE.rst
odoo/addons/stock_picking_late_activity/readme/CONTRIBUTORS.rst
odoo/addons/stock_picking_late_activity/readme/DESCRIPTION.rst
odoo/addons/stock_picking_late_activity/static/description/icon.png
odoo/addons/stock_picking_late_activity/static/description/index.html
odoo/addons/stock_picking_late_activity/tests/__init__.py
odoo/addons/stock_picking_late_activity/tests/test_stock_picking_late_activity.py
odoo/addons/stock_picking_late_activity/views/stock_picking_views.xml
odoo12_addon_stock_picking_late_activity-12.0.1.0.0.99.dev3.dist-info/METADATA
odoo12_addon_stock_picking_late_activity-12.0.1.0.0.99.dev3.dist-info/WHEEL
odoo12_addon_stock_picking_late_activity-12.0.1.0.0.99.dev3.dist-info/top_level.txt
odoo12_addon_stock_picking_late_activity-12.0.1.0.0.99.dev3.dist-info/RECORD
